jupyterlab_remote_url/__init__.py
jupyterlab_remote_url/_version.py
jupyterlab_remote_url/handlers.py
jupyterlab_remote_url-0.1.1.data/data/etc/jupyter/jupyter_notebook_config.d/jupyterlab_remote_url.json
jupyterlab_remote_url-0.1.1.data/data/etc/jupyter/jupyter_server_config.d/jupyterlab_remote_url.json
jupyterlab_remote_url-0.1.1.data/data/share/jupyter/labextensions/jupyterlab_remote_url/package.json
jupyterlab_remote_url-0.1.1.data/data/share/jupyter/labextensions/jupyterlab_remote_url/schemas/jupyterlab_remote_url/package.json.orig
jupyterlab_remote_url-0.1.1.data/data/share/jupyter/labextensions/jupyterlab_remote_url/schemas/jupyterlab_remote_url/plugin.json
jupyterlab_remote_url-0.1.1.data/data/share/jupyter/labextensions/jupyterlab_remote_url/static/747.2ca5f859b0b386f6563a.js
jupyterlab_remote_url-0.1.1.data/data/share/jupyter/labextensions/jupyterlab_remote_url/static/763.5dc75c521b77226162ba.js
jupyterlab_remote_url-0.1.1.data/data/share/jupyter/labextensions/jupyterlab_remote_url/static/remoteEntry.e1df4a7721d8fbe0f7da.js
jupyterlab_remote_url-0.1.1.data/data/share/jupyter/labextensions/jupyterlab_remote_url/static/style.js
jupyterlab_remote_url-0.1.1.data/data/share/jupyter/labextensions/jupyterlab_remote_url/static/third-party-licenses.json
jupyterlab_remote_url-0.1.1.data/data/share/jupyter/labextensions/jupyterlab_remote_url/install.json
jupyterlab_remote_url-0.1.1.dist-info/METADATA
jupyterlab_remote_url-0.1.1.dist-info/WHEEL
jupyterlab_remote_url-0.1.1.dist-info/licenses/LICENSE
jupyterlab_remote_url-0.1.1.dist-info/RECORD
