Metadata-Version: 2.1
Name: jupyterlab_remote_url
Version: 0.1.1
Summary: A JupyterLab extension to help set up a remote connection to the Jupyter server.
Project-URL: Homepage, https://github.com/sanderploegsma/jupyterlab_remote_url
Project-URL: Bug Tracker, https://github.com/sanderploegsma/jupyterlab_remote_url/issues
Project-URL: Repository, https://github.com/sanderploegsma/jupyterlab_remote_url.git
Author-email: Sander Ploegsma <sanderploegsma@gmail.com>
License: BSD 3-Clause License
License-File: LICENSE
Classifier: Framework :: Jupyter
Classifier: Framework :: Jupyter :: JupyterLab
Classifier: Framework :: Jupyter :: JupyterLab :: 3
Classifier: Framework :: Jupyter :: JupyterLab :: Extensions
Classifier: Framework :: Jupyter :: JupyterLab :: Extensions :: Prebuilt
Classifier: License :: OSI Approved :: BSD License
Classifier: Programming Language :: Python
Classifier: Programming Language :: Python :: 3
Classifier: Programming Language :: Python :: 3.8
Classifier: Programming Language :: Python :: 3.9
Classifier: Programming Language :: Python :: 3.10
Classifier: Programming Language :: Python :: 3.11
Requires-Python: >=3.8
Requires-Dist: jupyter-server<3,>=2.0.1
